pymoskito/__init__.py
pymoskito/binding_modules.py
pymoskito/controltools.py
pymoskito/examples/__init__.py
pymoskito/examples/ballbeam/__init__.py
pymoskito/examples/ballbeam/__main__.py
pymoskito/examples/ballbeam/ball_and_beam.png
pymoskito/examples/ballbeam/controller.py
pymoskito/examples/ballbeam/default.sreg
pymoskito/examples/ballbeam/feedforward.py
pymoskito/examples/ballbeam/lagrange.py
pymoskito/examples/ballbeam/linearization.py
pymoskito/examples/ballbeam/metaprocessing.py
pymoskito/examples/ballbeam/model.py
pymoskito/examples/ballbeam/observer.py
pymoskito/examples/ballbeam/postprocessing.py
pymoskito/examples/ballbeam/pp_regimes.sreg
pymoskito/examples/ballbeam/settings.py
pymoskito/examples/ballbeam/utils/A2_head.sray
pymoskito/examples/ballbeam/utils/A3_head.sray
pymoskito/examples/ballbeam/utils/B_head.sray
pymoskito/examples/ballbeam/utils/C2_head.sray
pymoskito/examples/ballbeam/utils/__init__.py
pymoskito/examples/ballbeam/utils/regimeGeneratorA1.py
pymoskito/examples/ballbeam/utils/regimeGeneratorA2_r0sweep.py
pymoskito/examples/ballbeam/utils/regimeGeneratorA2_r0sweep_forAmpl.py
pymoskito/examples/ballbeam/utils/regimeGeneratorA2r0.py
pymoskito/examples/ballbeam/utils/regimeGeneratorA2r0_forAmpl.py
pymoskito/examples/ballbeam/utils/regimeGeneratorA3.py
pymoskito/examples/ballbeam/utils/regimeGeneratorB.py
pymoskito/examples/ballbeam/utils/regimeGeneratorB1.py
pymoskito/examples/ballbeam/utils/regimeGeneratorB2.py
pymoskito/examples/ballbeam/utils/regimeGeneratorC1.py
pymoskito/examples/ballbeam/utils/regimeGeneratorC2.py
pymoskito/examples/ballbeam/utils/regimeGeneratorC_Observer.py
pymoskito/examples/ballbeam/visualization.py
pymoskito/examples/balltube/__init__.py
pymoskito/examples/balltube/__main__.py
pymoskito/examples/balltube/ball_in_tube.png
pymoskito/examples/balltube/default.sreg
pymoskito/examples/balltube/experiments.sreg
pymoskito/examples/balltube/feedforward.py
pymoskito/examples/balltube/model.py
pymoskito-0.5.0.dist-info/WHEEL
pymoskito-0.5.0.dist-info/METADATA
pymoskito-0.5.0.dist-info/RECORD
