Metadata-Version: 2.3
Name: pymoskito
Version: 0.5.0
Summary: Python based modular simulation & postprocessing kickass toolbox
Keywords: pymoskito control simulation feedback feedforward
Author: Stefan Ecklebe
Author-email: Stefan Ecklebe <stefan.ecklebe@umit-tirol.at>
License: GPLv3
Classifier: Development Status :: 5 - Production/Stable
Classifier: Intended Audience :: Developers
Classifier: Natural Language :: English
Classifier: Programming Language :: Python :: 3.8
Classifier: Programming Language :: Python :: 3.9
Classifier: Programming Language :: Python :: 3.10
Classifier: Programming Language :: Python :: 3.11
Classifier: Programming Language :: Python :: 3.12
Classifier: Programming Language :: Python :: 3.13
Requires-Dist: wheel>=0.38.1
Requires-Dist: sympy>=1.11
Requires-Dist: scipy>=1.10.1
Requires-Dist: numpy>=1.24.1
Requires-Dist: control>=0.9.0
Requires-Dist: pyyaml>=3.12
Requires-Dist: pandas>=1.5.3
Requires-Dist: pyqtgraph>=0.13.0
Requires-Dist: matplotlib>=3.6.0
Requires-Dist: pyqt5>=5.15
Requires-Dist: pyqt5-qt5==5.15.2 ; sys_platform == 'win32'
Requires-Dist: vtk>=6.3.0 ; extra == '3d'
Requires-Dist: pybind11>=2.7.0 ; extra == 'cpp'
Requires-Dist: docutils ; extra == 'docs'
Requires-Dist: sphinx>=1.4.9 ; extra == 'docs'
Requires-Dist: sphinx-rtd-dark-mode ; extra == 'docs'
Requires-Dist: sphinxcontrib-tikz>=0.4.7 ; extra == 'docs'
Requires-Python: >=3.8
Project-URL: Homepage, https://github.com/cklb/pymoskito
Provides-Extra: 3d
Provides-Extra: cpp
Provides-Extra: docs
